ipydraw/__init__.py
ipydraw/_frontend.py
ipydraw/_version.py
ipydraw/canvas.py
ipydraw/pointpicker.py
ipydraw/utils.py
ipydraw/labextension/package.json
ipydraw/labextension/static/480.b90a6722c21a9b12ea5d.js
ipydraw/labextension/static/568.87a8111643816d99d18e.js
ipydraw/labextension/static/remoteEntry.a8e2c31ed50c21bf097b.js
ipydraw/labextension/static/style.js
ipydraw/nbextension/extension.js
ipydraw/nbextension/index.js
ipydraw/nbextension/index.js.map
ipydraw-0.2.2.data/data/etc/jupyter/nbconfig/notebook.d/ipydraw.json
ipydraw-0.2.2.data/data/share/jupyter/labextensions/ipydraw/install.json
ipydraw-0.2.2.data/data/share/jupyter/labextensions/ipydraw/package.json
ipydraw-0.2.2.data/data/share/jupyter/labextensions/ipydraw/static/480.b90a6722c21a9b12ea5d.js
ipydraw-0.2.2.data/data/share/jupyter/labextensions/ipydraw/static/568.87a8111643816d99d18e.js
ipydraw-0.2.2.data/data/share/jupyter/labextensions/ipydraw/static/remoteEntry.a8e2c31ed50c21bf097b.js
ipydraw-0.2.2.data/data/share/jupyter/labextensions/ipydraw/static/style.js
ipydraw-0.2.2.data/data/share/jupyter/nbextensions/ipydraw/extension.js
ipydraw-0.2.2.data/data/share/jupyter/nbextensions/ipydraw/index.js
ipydraw-0.2.2.data/data/share/jupyter/nbextensions/ipydraw/index.js.map
ipydraw-0.2.2.dist-info/LICENSE.txt
ipydraw-0.2.2.dist-info/METADATA
ipydraw-0.2.2.dist-info/WHEEL
ipydraw-0.2.2.dist-info/top_level.txt
ipydraw-0.2.2.dist-info/RECORD
